ioant_mysqlhelper/__init__.py
ioant_mysqlhelper/db/__init__.py
ioant_mysqlhelper/db/db.py
ioant_mysqlhelper-0.1.2.dist-info/DESCRIPTION.rst
ioant_mysqlhelper-0.1.2.dist-info/METADATA
ioant_mysqlhelper-0.1.2.dist-info/RECORD
ioant_mysqlhelper-0.1.2.dist-info/WHEEL
ioant_mysqlhelper-0.1.2.dist-info/metadata.json
ioant_mysqlhelper-0.1.2.dist-info/top_level.txt
