Metadata-Version: 2.0
Name: ioant-mysqlhelper
Version: 0.1.2
Summary: This package is used for python scripts in IOAnt solution using mysql
Home-page: http://ioant.com
Author: Adam Saxen
Author-email: adam@asaxen.com
License: MIT
Platform: UNKNOWN
Requires-Dist: MySQL-python (>=1.2.5)
Requires-Dist: nose (>=1.3.7)
